unifyconnectorframework/__init__.py
unifyconnectorframework/config_not_found_error.py
unifyconnectorframework/connector.py
unifyconnectorframework/connector_handler.py
unifyconnectorframework/logging.py
unifyconnectorframework/organization_client.py
unifyconnectorframework/utils.py
unify_connector_framework-1.0.2.dist-info/LICENSE
unify_connector_framework-1.0.2.dist-info/METADATA
unify_connector_framework-1.0.2.dist-info/WHEEL
unify_connector_framework-1.0.2.dist-info/top_level.txt
unify_connector_framework-1.0.2.dist-info/RECORD
