Metadata-Version: 2.1
Name: unify-connector-framework
Version: 1.0.2
Summary: Develop connectors for Element Unify with the Connector Framework
Home-page: https://github.com/ElementAnalytics/unify-python-agents-common
Author: Element Analytics
Author-email: platform@ean.io
License: UNKNOWN
Platform: UNKNOWN
Classifier: Programming Language :: Python :: 3
Classifier: Programming Language :: Python :: 3.7
Requires-Python: >=3
License-File: LICENSE
Requires-Dist: unify-sdk (>=3.0.11)
Requires-Dist: croniter
Requires-Dist: keyring
